[{"name":"야키니쿠","url":"https://smartstore.naver.com/woowakgoods/products/9796867116","options":[{"name":"S","remain":175,"total":312},{"name":"M","remain":723,"total":922},{"name":"L","remain":1051,"total":1236},{"name":"XL","remain":484,"total":598}]},{"name":"경찰행동","url":"https://smartstore.naver.com/woowakgoods/products/9796952622","options":[{"name":"S","remain":226,"total":301},{"name":"M","remain":783,"total":924},{"name":"L","remain":1083,"total":1238},{"name":"XL","remain":497,"total":579}]},{"name":"페리도두","url":"https://smartstore.naver.com/woowakgoods/products/9797085511","options":[{"name":"S","remain":157,"total":308},{"name":"M","remain":457,"total":921},{"name":"L","remain":728,"total":1225},{"name":"XL","remain":254,"total":615}]},{"name":"본룸","url":"https://smartstore.naver.com/woowakgoods/products/9797165087","options":[{"name":"S","remain":0,"total":283},{"name":"M","remain":200,"total":865},{"name":"L","remain":327,"total":1155},{"name":"XL","remain":0,"total":568}]},{"name":"아르체타","url":"https://smartstore.naver.com/woowakgoods/products/9797191408","options":[{"name":"S","remain":300,"total":609},{"name":"M","remain":1101,"total":1804},{"name":"L","remain":1492,"total":2415},{"name":"XL","remain":506,"total":1195}]}]